{
  "content": [
    {
      "path": ".gitattributes",
      "size": 66,
      "date": 132771374234493388
    },
    {
      "path": "de-DE.locPak",
      "size": 2305,
      "date": 132770333540015341
    },
    {
      "path": "en-US.locPak",
      "size": 1908,
      "date": 132752560619509699
    },
    {
      "path": "es-ES.locPak",
      "size": 2102,
      "date": 132770333596554000
    },
    {
      "path": "fr-FR.locPak",
      "size": 2152,
      "date": 132770333673083267
    },
    {
      "path": "it-IT.locPak",
      "size": 2116,
      "date": 132770333729780562
    },
    {
      "path": "pl-PL.locPak",
      "size": 2253,
      "date": 132770333768456720
    },
    {
      "path": "pt-BR.locPak",
      "size": 2054,
      "date": 132770333806028499
    },
    {
      "path": "ru-RU.locPak",
      "size": 3069,
      "date": 132770333847743214
    },
    {
      "path": ".git/COMMIT_EDITMSG",
      "size": 15,
      "date": 132771374237126344
    },
    {
      "path": ".git/config",
      "size": 130,
      "date": 132771374226109030
    },
    {
      "path": ".git/description",
      "size": 73,
      "date": 132771374225261315
    },
    {
      "path": ".git/HEAD",
      "size": 21,
      "date": 132771374225849724
    },
    {
      "path": ".git/index",
      "size": 4757,
      "date": 132771374979025558
    },
    {
      "path": ".git/hooks/applypatch-msg.sample",
      "size": 478,
      "date": 132771374225341084
    },
    {
      "path": ".git/hooks/commit-msg.sample",
      "size": 896,
      "date": 132771374225400924
    },
    {
      "path": ".git/hooks/fsmonitor-watchman.sample",
      "size": 4655,
      "date": 132771374225440818
    },
    {
      "path": ".git/hooks/post-update.sample",
      "size": 189,
      "date": 132771374225480712
    },
    {
      "path": ".git/hooks/pre-applypatch.sample",
      "size": 424,
      "date": 132771374225510631
    },
    {
      "path": ".git/hooks/pre-commit.sample",
      "size": 1643,
      "date": 132771374225560501
    },
    {
      "path": ".git/hooks/pre-merge-commit.sample",
      "size": 416,
      "date": 132771374225600392
    },
    {
      "path": ".git/hooks/pre-push.sample",
      "size": 1374,
      "date": 132771374225660232
    },
    {
      "path": ".git/hooks/pre-rebase.sample",
      "size": 4898,
      "date": 132771374225720071
    },
    {
      "path": ".git/hooks/pre-receive.sample",
      "size": 544,
      "date": 132771374225759963
    },
    {
      "path": ".git/hooks/prepare-commit-msg.sample",
      "size": 1492,
      "date": 132771374225789885
    },
    {
      "path": ".git/hooks/update.sample",
      "size": 3650,
      "date": 132771374225829780
    },
    {
      "path": ".git/info/exclude",
      "size": 240,
      "date": 132771374225839761
    },
    {
      "path": ".git/logs/HEAD",
      "size": 194,
      "date": 132771374237275941
    },
    {
      "path": ".git/logs/refs/heads/main",
      "size": 194,
      "date": 132771374237275941
    },
    {
      "path": ".git/objects/05/1b9776c03f6b59854c2f050253a5604c8d8da5",
      "size": 4345,
      "date": 132771374236308536
    },
    {
      "path": ".git/objects/08/eebb1bc7d45202f9342c9d6568505245254963",
      "size": 3233,
      "date": 132771374236368379
    },
    {
      "path": ".git/objects/0b/79066697a65aefdb7c1f89bfcecc4c6ddfb61f",
      "size": 5295,
      "date": 132771374236238720
    },
    {
      "path": ".git/objects/13/1db917acbb3bffebb8abf29e941b93e6a15e20",
      "size": 37,
      "date": 132771374235889660
    },
    {
      "path": ".git/objects/19/86bf60b33f9e1e78098bf82f68490c4c2f84b5",
      "size": 349,
      "date": 132771374236936845
    },
    {
      "path": ".git/objects/1c/1a0a2ac69a749911be8018b2833f854a24970e",
      "size": 122,
      "date": 132771374235979409
    },
    {
      "path": ".git/objects/24/6e9840684f620e59e9d8070ae78acaf11da50e",
      "size": 81,
      "date": 132771374237036587
    },
    {
      "path": ".git/objects/26/f36fa192f85d0392a1e38080a9a7e45184b2ad",
      "size": 3658,
      "date": 132771374236228754
    },
    {
      "path": ".git/objects/2d/14ef5c07ef10a6fa3ff48d1cfb6ac22b748b34",
      "size": 854,
      "date": 132771374236438191
    },
    {
      "path": ".git/objects/37/4cf628859923431560edc9a39722885a7cd136",
      "size": 1303,
      "date": 132771374236378353
    },
    {
      "path": ".git/objects/37/bfd673e5462144f8fb765fc560ea3ff6e3826a",
      "size": 171,
      "date": 132771374236877019
    },
    {
      "path": ".git/objects/38/7150d2363776234c3f33338454f7de7998164a",
      "size": 1205,
      "date": 132771374236418250
    },
    {
      "path": ".git/objects/38/82685bd0c6555c9fa7cada4699e5a9f50fcc0a",
      "size": 127,
      "date": 132771374236966766
    },
    {
      "path": ".git/objects/38/a8f8ed669574dca5cb858ecde6687bea2bab1f",
      "size": 506,
      "date": 132771374235610395
    },
    {
      "path": ".git/objects/38/af9c91fd6fff20c639d25278395f73e0f69594",
      "size": 404,
      "date": 132771374236198827
    },
    {
      "path": ".git/objects/3e/d3c5a07e3108e331c9364f98131ca89e3f3ff7",
      "size": 4235,
      "date": 132771374235839786
    },
    {
      "path": ".git/objects/48/d8897256c962d6bdd3d80e5de38765b200ea00",
      "size": 117,
      "date": 132771374237006657
    },
    {
      "path": ".git/objects/4b/80c1385f55aa806f8d1454a54508f561948631",
      "size": 20938,
      "date": 132771374235969432
    },
    {
      "path": ".git/objects/4b/b4471533984277a07e0cc7ae6bc8d2b5cba827",
      "size": 524,
      "date": 132771374235690177
    },
    {
      "path": ".git/objects/4f/8a297cc57926685811017451052f26f2b4b5fc",
      "size": 59,
      "date": 132771374237076477
    },
    {
      "path": ".git/objects/53/c357315bcb696d2b754374cc22c146f22ec5a0",
      "size": 544,
      "date": 132771374235640322
    },
    {
      "path": ".git/objects/56/5a5b2a7b4e1b3f3db692d8a7fe2a81d4e1a90d",
      "size": 6194,
      "date": 132771374235720105
    },
    {
      "path": ".git/objects/59/af7bc4fdea28844e6d577c408959d256348f80",
      "size": 1148,
      "date": 132771374236408278
    },
    {
      "path": ".git/objects/59/b5d3de395a9d451834ab05bc5bc4c28b620046",
      "size": 69,
      "date": 132771374236986718
    },
    {
      "path": ".git/objects/71/3cebb6260b8e3b938dfb5020f1b62ba6135930",
      "size": 871,
      "date": 132771374235929540
    },
    {
      "path": ".git/objects/73/87d70b925e0269dca690693c27338d7d9c028d",
      "size": 65,
      "date": 132771374236947062
    },
    {
      "path": ".git/objects/75/95736911e8db60ce58ceb56f18d9d4fa332acd",
      "size": 346,
      "date": 132771374236268641
    },
    {
      "path": ".git/objects/7a/17f8c50897b7ad10b42ffcf01e3fe61f784dbd",
      "size": 335,
      "date": 132771374237056530
    },
    {
      "path": ".git/objects/7e/4bec1163dc56474936a63f418e111fd293c933",
      "size": 526,
      "date": 132771374235660271
    },
    {
      "path": ".git/objects/84/865cd0bd6f10ed6564d871568e8d53cb90b5d4",
      "size": 502,
      "date": 132771374235620367
    },
    {
      "path": ".git/objects/8b/6e78bc0492f4c382d543a7df26591df5b17d43",
      "size": 136,
      "date": 132771374235820112
    },
    {
      "path": ".git/objects/8f/669eaac08779e86c5342ebac88419b5cba17f0",
      "size": 513,
      "date": 132771374235590451
    },
    {
      "path": ".git/objects/97/ebce8f451a737a067112b3f6b9739d23923e69",
      "size": 1075,
      "date": 132771374236398305
    },
    {
      "path": ".git/objects/99/fe1c3fd39f338561d30f43c497b6d714ca13fe",
      "size": 1497,
      "date": 132771374236488059
    },
    {
      "path": ".git/objects/a5/9060307471a052ad3db0945d254af380525c9f",
      "size": 69,
      "date": 132771374237016895
    },
    {
      "path": ".git/objects/b6/d05629ee0d9c5276339ed010dca3c6ab68315a",
      "size": 701,
      "date": 132771374235650293
    },
    {
      "path": ".git/objects/b9/8e4f059ec29a1853bd75b3953bae65ed18a078",
      "size": 1166,
      "date": 132771374236428220
    },
    {
      "path": ".git/objects/bb/ad31610d690aa04d016f1fe0f3bc28ae351a98",
      "size": 1350,
      "date": 132771374235909607
    },
    {
      "path": ".git/objects/c8/06b40cf708544359aac6f8acfe1d8e529249a8",
      "size": 5212,
      "date": 132771374236258660
    },
    {
      "path": ".git/objects/ca/81e7ca586c460ea08d3d38e47da4ab26265e98",
      "size": 512,
      "date": 132771374235680211
    },
    {
      "path": ".git/objects/cf/0d89a268296928aa71e93cd0d79810df811a0a",
      "size": 53,
      "date": 132771374237046564
    },
    {
      "path": ".git/objects/d3/19f089907a000db8c017dc5cdfe2047b997e9b",
      "size": 2515,
      "date": 132771374235899634
    },
    {
      "path": ".git/objects/d6/8fa670fe75c483fe5700c5426b8390ba4bcebf",
      "size": 1517,
      "date": 132771374236218769
    },
    {
      "path": ".git/objects/db/5806dc79c186a110c9c3f374fb7bd6cee0e6fb",
      "size": 358542,
      "date": 132771374236178879
    },
    {
      "path": ".git/objects/dd/46b5f68e46d230fe9f14f023c8d656a407e5b4",
      "size": 475,
      "date": 132771374237106397
    },
    {
      "path": ".git/objects/df/e0770424b2a19faf507a501ebfc23be8f54e7b",
      "size": 76,
      "date": 132771374235510660
    },
    {
      "path": ".git/objects/e3/0c63b3159f74ac45d90401c26b2323cd0ca246",
      "size": 1305,
      "date": 132771374236458138
    },
    {
      "path": ".git/objects/e3/7549a7417a8b94d414af9e7f470455538f66a9",
      "size": 1163,
      "date": 132771374236468113
    },
    {
      "path": ".git/objects/e9/7c336ccecf064276bf88eab0d75e4f8c336184",
      "size": 298,
      "date": 132771374236448165
    },
    {
      "path": ".git/objects/f5/e936f6997dadfee7d368d8e1615ee9bebc7892",
      "size": 51,
      "date": 132771374237086448
    },
    {
      "path": ".git/objects/f9/d7b3ec3a2a3d8ad0d4282704bc5fda70f4ca6e",
      "size": 632,
      "date": 132771374235570503
    },
    {
      "path": ".git/objects/fa/2edd2b92ca7e3414121ea4d47736085a81f490",
      "size": 4560,
      "date": 132771374236288593
    },
    {
      "path": ".git/objects/fa/bde1686e0973b8bbbad7de4f27facca73fcd41",
      "size": 148,
      "date": 132771374237216103
    },
    {
      "path": ".git/objects/fe/d6971105f40abbf1d88675b60014e2c8086936",
      "size": 47,
      "date": 132771374236976745
    },
    {
      "path": ".git/refs/heads/main",
      "size": 41,
      "date": 132771374237266247
    },
    {
      "path": "Effects/LIGHT_G36_BeaconTop.fx",
      "size": 3501,
      "date": 132721075575904605
    },
    {
      "path": "Effects/LIGHT_G36_Landing.fx",
      "size": 1160,
      "date": 132721075576004058
    },
    {
      "path": "Effects/LIGHT_G36_NavigationGreen.fx",
      "size": 1158,
      "date": 132721075576103786
    },
    {
      "path": "Effects/LIGHT_G36_NavigationRed.fx",
      "size": 1155,
      "date": 132721075576203824
    },
    {
      "path": "Effects/LIGHT_G36_NavigationWhite.fx",
      "size": 1353,
      "date": 132721075576313232
    },
    {
      "path": "Effects/LIGHT_G36_StrobeSimple.fx",
      "size": 4422,
      "date": 132721075576412967
    },
    {
      "path": "Effects/LIGHT_G36_Taxi.fx",
      "size": 1209,
      "date": 132721075576512968
    },
    {
      "path": "Effects/LIGHT_G36_vLanding.fx",
      "size": 1157,
      "date": 132721075576622502
    },
    {
      "path": "Effects/LIGHT_G36_vTaxi.fx",
      "size": 1206,
      "date": 132721075576722139
    },
    {
      "path": "Effects/texture/FX_ulm01.PNG.dds",
      "size": 87556,
      "date": 132721075577011282
    },
    {
      "path": "Effects/texture/fx_ulm01.png.DDS.FLAGS",
      "size": 21,
      "date": 132721075577380576
    },
    {
      "path": "Effects/texture/FX_ulm01.PNG.DDS.json",
      "size": 144,
      "date": 132721075576851994
    },
    {
      "path": "Effects/texture/FX_ulm03.PNG.dds",
      "size": 87556,
      "date": 132721075577270874
    },
    {
      "path": "Effects/texture/fx_ulm03.png.DDS.FLAGS",
      "size": 21,
      "date": 132721075577480034
    },
    {
      "path": "Effects/texture/FX_ulm03.PNG.DDS.json",
      "size": 144,
      "date": 132721075577111298
    },
    {
      "path": "ModelBehaviorDefs/Asobo/Exterior.xml",
      "size": 72506,
      "date": 132721075577752203
    },
    {
      "path": "ModelBehaviorDefs/G36X/CustomLogic.xml",
      "size": 9290,
      "date": 132721075577941411
    },
    {
      "path": "ModelBehaviorDefs/G36X/CustomTemplates.xml",
      "size": 6011,
      "date": 132721075578071082
    },
    {
      "path": "ModelBehaviorDefs/G36X/Subtemplates/G36_Subtemplates.xml",
      "size": 3473,
      "date": 132721075578230641
    },
    {
      "path": "SimObjects/Airplanes/Asobo_Bonanza_G36/ai.cfg",
      "size": 721,
      "date": 132721075573076191
    },
    {
      "path": "SimObjects/Airplanes/Asobo_Bonanza_G36/aircraft.cfg",
      "size": 3056,
      "date": 132771376868768945
    },
    {
      "path": "SimObjects/Airplanes/Asobo_Bonanza_G36/engines.cfg",
      "size": 9360,
      "date": 132721075573215874
    },
    {
      "path": "SimObjects/Airplanes/Asobo_Bonanza_G36/flight_model.cfg",
      "size": 15909,
      "date": 132771376573792271
    },
    {
      "path": "SimObjects/Airplanes/Asobo_Bonanza_G36/systems.cfg",
      "size": 11987,
      "date": 132770720423506289
    },
    {
      "path": "SimObjects/Airplanes/Asobo_Bonanza_G36/Checklist/Bonanza_G36_Checklist.xml",
      "size": 148411,
      "date": 132721075573784680
    },
    {
      "path": "SimObjects/Airplanes/Asobo_Bonanza_G36/model/Bonanza_g36_interior.xml",
      "size": 22923,
      "date": 132721075574343485
    },
    {
      "path": "SimObjects/Airplanes/Asobo_Bonanza_G36/panel/panel.cfg",
      "size": 826,
      "date": 132721075574492786
    },
    {
      "path": "SimObjects/Airplanes/Asobo_Bonanza_G36/panel/panel.xml",
      "size": 26936,
      "date": 132771243813042893
    },
    {
      "path": "SimObjects/Airplanes/Asobo_Bonanza_G36/sound/sound.xml",
      "size": 28710,
      "date": 132723174527109242
    },
    {
      "path": "SimObjects/Airplanes/Asobo_Bonanza_G36/TEXTURE/BONANZA_COCKPIT_DECALS_02_ALBD.PNG.dds",
      "size": 1398256,
      "date": 132721075574143937
    },
    {
      "path": "SimObjects/Airplanes/Asobo_Bonanza_G36/TEXTURE/BONANZA_COCKPIT_DECALS_02_ALBD.PNG.DDS.json",
      "size": 120,
      "date": 132721075573924307
    }
  ]
}